MANIFEST.in
README.rst
setup.cfg
setup.py
collective/__init__.py
collective.optimage.egg-info/PKG-INFO
collective.optimage.egg-info/SOURCES.txt
collective.optimage.egg-info/dependency_links.txt
collective.optimage.egg-info/entry_points.txt
collective.optimage.egg-info/namespace_packages.txt
collective.optimage.egg-info/not-zip-safe
collective.optimage.egg-info/requires.txt
collective.optimage.egg-info/top_level.txt
collective/optimage/__init__.py
collective/optimage/all.zcml
collective/optimage/configure.zcml
collective/optimage/events.py
collective/optimage/gifsicle.zcml
collective/optimage/interfaces.py
collective/optimage/jpegoptim.zcml
collective/optimage/jpegtran.zcml
collective/optimage/optipng.zcml
collective/optimage/pngcrush.zcml
collective/optimage/pngout.zcml
collective/optimage/adapters/__init__.py
collective/optimage/adapters/core.py
collective/optimage/adapters/gifsicle.py
collective/optimage/adapters/jpegoptim.py
collective/optimage/adapters/jpegtran.py
collective/optimage/adapters/optipng.py
collective/optimage/adapters/pngcrush.py
collective/optimage/adapters/pngout.py
docs/HISTORY.txt
docs/INSTALL.txt
docs/LICENSE.GPL
docs/LICENSE.txt