Metadata-Version: 1.0
Name: collective.optimage
Version: 0.1.0a
Summary: Optimize Plone content images from Web usage
Home-page: http://plone.org/products/collective.optimage
Author: keul
Author-email: luca@keul.it
License: GPL
Keywords: plone image optimization web jpegoptim optipng
Platform: UNKNOWN
Classifier: Framework :: Plone
Classifier: Framework :: Plone :: 4.0
Classifier: Framework :: Plone :: 4.1
Classifier: Framework :: Plone :: 4.2
Classifier: Programming Language :: Python
